{"id": 4856, "title": "Ticket #4856: Enable ENCRYPT_EXECUTE_DIRECTORY on Linux and from submit file", "description": "<blockquote>\nCurrently, encryption of the execute directory is only available on Windows, and can only be enabled by the admin via the starter config knob ENCRYPT_EXECUTE_DIRECTORY.\n\n<p>This ticket will 1) allow the execute directory to be encrypted on Linux via ecryptfs, and 2) allow the user to require that the execute directory be encrypted in the job classad (implying the job can only match machines that are capable of this feat).</p></blockquote>", "remarks": "<blockquote>\n</blockquote>", "derived_tickets": "<table border=\"0\" cellpadding=\"0\" cellspacing=\"0\">\n<tbody><tr><td align=\"right\" valign=\"top\" width=\"160\">\n<span class=\"ticket\"><a class=\"resolved\" href=\"tktview?tn=4872\" title=\"Add ecryptfs-utils as dependency to binary packaging\">#4872</a></span></td>\n<td align=\"center\" valign=\"center\" width=\"30\">\n<span class=\"icon ptr1\">\u00a0</span></td>\n<td align=\"left\" valign=\"top\">\nAdd ecryptfs-utils as dependency to binary packaging</td></tr>\n</tbody></table>", "attachments": "", "check_ins": "<table border=\"0\" cellpadding=\"0\" cellspacing=\"0\">\n<tbody><tr><td align=\"right\" valign=\"top\" width=\"160\">2015-Feb-19 13:54</td>\n<td align=\"center\" valign=\"top\" width=\"30\">\n<span class=\"icon dot\">\u00a0</span></td>\n<td align=\"left\" valign=\"top\"> \nCheck-in <span class=\"chng\"><a href=\"chngview?cn=43420\">[43420]</a></span>: Add version history item for 2 8.3.3 known bugs. <span class=\"ticket\"><a class=\"resolved\" href=\"tktview?tn=4902\" title=\"OnExitHold on windows in local universe broken\">#4902</a></span> <span class=\"ticket\"><a class=\"resolved\" href=\"tktview?tn=4856\" title=\"Enable ENCRYPT_EXECUTE_DIRECTORY on Linux and from submit file\">#4856</a></span>  (By Karen Miller )</td></tr>\n<tr><td align=\"right\" valign=\"top\" width=\"160\">2015-Feb-19 13:11</td>\n<td align=\"center\" valign=\"top\" width=\"30\">\n<span class=\"icon dot\">\u00a0</span></td>\n<td align=\"left\" valign=\"top\"> \nCheck-in <span class=\"chng\"><a href=\"chngview?cn=43418\">[43418]</a></span>: edit new knob definitions for <span class=\"ticket\"><a class=\"resolved\" href=\"tktview?tn=4856\" title=\"Enable ENCRYPT_EXECUTE_DIRECTORY on Linux and from submit file\">#4856</a></span>  (By Karen Miller )</td></tr>\n<tr><td align=\"right\" valign=\"top\" width=\"160\">2015-Feb-19 12:22</td>\n<td align=\"center\" valign=\"top\" width=\"30\">\n<span class=\"icon dot\">\u00a0</span></td>\n<td align=\"left\" valign=\"top\"> \nCheck-in <span class=\"chng\"><a href=\"chngview?cn=43412\">[43412]</a></span>: Document knob DISCARD_SESSION_KEYRING_ON_STARTUP. <span class=\"ticket\"><a class=\"resolved\" href=\"tktview?tn=4856\" title=\"Enable ENCRYPT_EXECUTE_DIRECTORY on Linux and from submit file\">#4856</a></span>  (By Todd Tannenbaum )</td></tr>\n<tr><td align=\"right\" valign=\"top\" width=\"160\">2015-Feb-19 11:39</td>\n<td align=\"center\" valign=\"top\" width=\"30\">\n<span class=\"icon dot\">\u00a0</span></td>\n<td align=\"left\" valign=\"top\"> \nCheck-in <span class=\"chng\"><a href=\"chngview?cn=43411\">[43411]</a></span>: Documentation for knob ECRYPTFS_ADD_PASSPHRASE. <span class=\"ticket\"><a class=\"resolved\" href=\"tktview?tn=4856\" title=\"Enable ENCRYPT_EXECUTE_DIRECTORY on Linux and from submit file\">#4856</a></span>  (By Todd Tannenbaum )</td></tr>\n<tr><td align=\"right\" valign=\"top\" width=\"160\">2015-Feb-19 10:35</td>\n<td align=\"center\" valign=\"top\" width=\"30\">\n<span class=\"icon dot\">\u00a0</span></td>\n<td align=\"left\" valign=\"top\"> \nCheck-in <span class=\"chng\"><a href=\"chngview?cn=43414\">[43414]</a></span>: fix typo in version history item for <span class=\"ticket\"><a class=\"resolved\" href=\"tktview?tn=4856\" title=\"Enable ENCRYPT_EXECUTE_DIRECTORY on Linux and from submit file\">#4856</a></span>  (By Karen Miller )</td></tr>\n<tr><td align=\"right\" valign=\"top\" width=\"160\">2015-Feb-06 13:59</td>\n<td align=\"center\" valign=\"top\" width=\"30\">\n<span class=\"icon dot\">\u00a0</span></td>\n<td align=\"left\" valign=\"top\"> \nCheck-in <span class=\"chng\"><a href=\"chngview?cn=43277\">[43277]</a></span>: documentation edits for <span class=\"ticket\"><a class=\"resolved\" href=\"tktview?tn=4856\" title=\"Enable ENCRYPT_EXECUTE_DIRECTORY on Linux and from submit file\">#4856</a></span>  (By Karen Miller )</td></tr>\n<tr><td align=\"right\" valign=\"top\" width=\"160\">2015-Feb-06 10:16</td>\n<td align=\"center\" valign=\"top\" width=\"30\">\n<span class=\"icon dot\">\u00a0</span></td>\n<td align=\"left\" valign=\"top\"> \nCheck-in <span class=\"chng\"><a href=\"chngview?cn=43272\">[43272]</a></span>: Version history entry for encrypt_execute_directory enhancements. <span class=\"ticket\"><a class=\"resolved\" href=\"tktview?tn=4856\" title=\"Enable ENCRYPT_EXECUTE_DIRECTORY on Linux and from submit file\">#4856</a></span>  (By Todd Tannenbaum )</td></tr>\n<tr><td align=\"right\" valign=\"top\" width=\"160\">2015-Feb-06 10:08</td>\n<td align=\"center\" valign=\"top\" width=\"30\">\n<span class=\"icon dot\">\u00a0</span></td>\n<td align=\"left\" valign=\"top\"> \nCheck-in <span class=\"chng\"><a href=\"chngview?cn=43271\">[43271]</a></span>: Documentation for encrypt_execute_directory changes. <span class=\"ticket\"><a class=\"resolved\" href=\"tktview?tn=4856\" title=\"Enable ENCRYPT_EXECUTE_DIRECTORY on Linux and from submit file\">#4856</a></span>  (By Todd Tannenbaum )</td></tr>\n<tr><td align=\"right\" valign=\"top\" width=\"160\">2015-Feb-03 11:47</td>\n<td align=\"center\" valign=\"top\" width=\"30\">\n<span class=\"icon dot\">\u00a0</span></td>\n<td align=\"left\" valign=\"top\"> \nCheck-in <span class=\"chng\"><a href=\"chngview?cn=43218\">[43218]</a></span>: Always include syscall.h, needed for encrypted execute directory keys. <span class=\"ticket\"><a class=\"resolved\" href=\"tktview?tn=4856\" title=\"Enable ENCRYPT_EXECUTE_DIRECTORY on Linux and from submit file\">#4856</a></span>  (By Jaime Frey )</td></tr>\n<tr><td align=\"right\" valign=\"top\" width=\"160\">2015-Feb-02 17:32</td>\n<td align=\"center\" valign=\"top\" width=\"30\">\n<span class=\"icon dot\">\u00a0</span></td>\n<td align=\"left\" valign=\"top\"> \nCheck-in <span class=\"chng\"><a href=\"chngview?cn=42525\">[42525]</a></span>: If encrypt_execute_directory is True, encrypt /tmp and /var/tmp. <span class=\"ticket\"><a class=\"resolved\" href=\"tktview?tn=4856\" title=\"Enable ENCRYPT_EXECUTE_DIRECTORY on Linux and from submit file\">#4856</a></span> We do this by simply adding /tmp,/var/tmp to MOUNT_UNDER_SCRATCH if the excute directory is encrypted.  (By Todd Tannenbaum )</td></tr>\n<tr><td align=\"right\" valign=\"top\" width=\"160\">2015-Feb-02 16:31</td>\n<td align=\"center\" valign=\"top\" width=\"30\">\n<span class=\"icon dot\">\u00a0</span></td>\n<td align=\"left\" valign=\"top\"> \nCheck-in <span class=\"chng\"><a href=\"chngview?cn=42522\">[42522]</a></span>: make g++ shut up about return value of write for <span class=\"ticket\"><a class=\"resolved\" href=\"tktview?tn=4856\" title=\"Enable ENCRYPT_EXECUTE_DIRECTORY on Linux and from submit file\">#4856</a></span>  (By John (TJ) Knoeller )</td></tr>\n<tr><td align=\"right\" valign=\"top\" width=\"160\">2015-Feb-02 14:44</td>\n<td align=\"center\" valign=\"top\" width=\"30\">\n<span class=\"icon dot\">\u00a0</span></td>\n<td align=\"left\" valign=\"top\"> \nCheck-in <span class=\"chng\"><a href=\"chngview?cn=42516\">[42516]</a></span>: Allow jobs to request encrypt_execute_directory in submit file. <span class=\"ticket\"><a class=\"resolved\" href=\"tktview?tn=4856\" title=\"Enable ENCRYPT_EXECUTE_DIRECTORY on Linux and from submit file\">#4856</a></span> In addition honoring admin desires to encrypt the execute directory via a knob in condor_config, allow users to specify it in the submit file on both Windows and Linux. This also requires the starter to advertise it as a capability\u00a0[...]\n (By Todd Tannenbaum )</td></tr>\n<tr><td align=\"right\" valign=\"top\" width=\"160\">2015-Feb-02 14:40</td>\n<td align=\"center\" valign=\"top\" width=\"30\">\n<span class=\"icon dot\">\u00a0</span></td>\n<td align=\"left\" valign=\"top\"> \nCheck-in <span class=\"chng\"><a href=\"chngview?cn=42515\">[42515]</a></span>: Fix compile warning on Fedora (check fscanf return val). <span class=\"ticket\"><a class=\"resolved\" href=\"tktview?tn=4856\" title=\"Enable ENCRYPT_EXECUTE_DIRECTORY on Linux and from submit file\">#4856</a></span>  (By Todd Tannenbaum )</td></tr>\n<tr><td align=\"right\" valign=\"top\" width=\"160\">2015-Feb-02 13:19</td>\n<td align=\"center\" valign=\"top\" width=\"30\">\n<span class=\"icon dot\">\u00a0</span></td>\n<td align=\"left\" valign=\"top\"> \nCheck-in <span class=\"chng\"><a href=\"chngview?cn=42507\">[42507]</a></span>: fix build break for non-clipped builds <span class=\"ticket\"><a class=\"resolved\" href=\"tktview?tn=4856\" title=\"Enable ENCRYPT_EXECUTE_DIRECTORY on Linux and from submit file\">#4856</a></span>  (By John (TJ) Knoeller )</td></tr>\n<tr><td align=\"right\" valign=\"top\" width=\"160\">2015-Jan-30 16:20</td>\n<td align=\"center\" valign=\"top\" width=\"30\">\n<span class=\"icon dot\">\u00a0</span></td>\n<td align=\"left\" valign=\"top\"> \nCheck-in <span class=\"chng\"><a href=\"chngview?cn=42500\">[42500]</a></span>: Implement ENCRYPT_EXECUTE_DIRETORY on Linux. <span class=\"ticket\"><a class=\"resolved\" href=\"tktview?tn=4856\" title=\"Enable ENCRYPT_EXECUTE_DIRECTORY on Linux and from submit file\">#4856</a></span> Encrypt the execute directory on linux via ecryptfs and private mount namespaces. If enabled, the startd will create a subdirectory in the execute dir, and while spawning the starter, the startd will perform an ecryptfs mount of this subdirectory in\u00a0[...]\n (By Todd Tannenbaum )</td></tr>\n<tr><td align=\"right\" valign=\"top\" width=\"160\">2015-Jan-30 14:32</td>\n<td align=\"center\" valign=\"top\" width=\"30\">\n<span class=\"icon dot\">\u00a0</span></td>\n<td align=\"left\" valign=\"top\"> \nCheck-in <span class=\"chng\"><a href=\"chngview?cn=42499\">[42499]</a></span>: Added method to fill a <span class=\"wiki\"><a class=\"missing\" href=\"wiki?p=MyString\" title=\"My String\">MyString</a></span> with a random password. <span class=\"ticket\"><a class=\"resolved\" href=\"tktview?tn=4856\" title=\"Enable ENCRYPT_EXECUTE_DIRECTORY on Linux and from submit file\">#4856</a></span>  (By Todd Tannenbaum )</td></tr>\n<tr><td align=\"right\" valign=\"top\" width=\"160\">2015-Jan-30 14:31</td>\n<td align=\"center\" valign=\"top\" width=\"30\">\n<span class=\"icon dot\">\u00a0</span></td>\n<td align=\"left\" valign=\"top\"> \nCheck-in <span class=\"chng\"><a href=\"chngview?cn=42498\">[42498]</a></span>: Utility function to check if linux kernel is version X or newer. <span class=\"ticket\"><a class=\"resolved\" href=\"tktview?tn=4856\" title=\"Enable ENCRYPT_EXECUTE_DIRECTORY on Linux and from submit file\">#4856</a></span>  (By Todd Tannenbaum )</td></tr>\n<tr><td align=\"right\" valign=\"top\" width=\"160\">2015-Jan-30 14:29</td>\n<td align=\"center\" valign=\"top\" width=\"30\">\n<span class=\"icon dot\">\u00a0</span></td>\n<td align=\"left\" valign=\"top\"> \nCheck-in <span class=\"chng\"><a href=\"chngview?cn=42497\">[42497]</a></span>: Enable my_popen() to both write and read from child on Linux. <span class=\"ticket\"><a class=\"resolved\" href=\"tktview?tn=4856\" title=\"Enable ENCRYPT_EXECUTE_DIRECTORY on Linux and from submit file\">#4856</a></span> Normally popen() can write to stdin or read from stdout/err, but not both. This change allows a small (2k) null-terminated buffer to be sent to the child's stdin when using my_popen in \"r\" mode on Linux.  (By Todd Tannenbaum )</td></tr>\n<tr><td align=\"right\" valign=\"top\" width=\"160\">2015-Jan-30 14:24</td>\n<td align=\"center\" valign=\"top\" width=\"30\">\n<span class=\"icon dot\">\u00a0</span></td>\n<td align=\"left\" valign=\"top\"> \nCheck-in <span class=\"chng\"><a href=\"chngview?cn=42496\">[42496]</a></span>: Add param_with_full_path() function to safely expand path of param. <span class=\"ticket\"><a class=\"resolved\" href=\"tktview?tn=4856\" title=\"Enable ENCRYPT_EXECUTE_DIRECTORY on Linux and from submit file\">#4856</a></span>  (By Todd Tannenbaum )</td></tr>\n</tbody></table>", "type": "enhance", "last_change": "2015-Feb-18 15:35", "status": "resolved", "created": "2015-Jan-30 12:08", "fixed_version": "2015-Jan-30 12:08", "broken_version": "", "priority": "2", "subsystem": "DaemonsExecNode", "assigned_to": "tannenba", "derived_from": "", "creator": "tannenba", "rust": "", "customer_group": "chtc", "visibility": "public", "notify": "", "due_date": ""}