{"id": 5564, "title": "Ticket #5564: Make a standard universe DAGMan test", "description": "<blockquote>\nI want to make a DAGMan test that has standard universe node jobs, partly to make sure my fix for <span class=\"ticket\"><a class=\"defer\" href=\"tktview?tn=5299\" title=\"Schedd doesn't correctly write nodes.log file for local universe jobs\">#5299</a></span> doesn't break anything for standard universe...  (See job_dagman_local).</blockquote>", "remarks": "<blockquote>\n</blockquote>", "derived_tickets": "", "attachments": "", "check_ins": "", "type": "enhance", "last_change": "2017-May-30 17:25", "status": "new", "created": "2016-Mar-16 14:01", "fixed_version": "2016-Mar-16 14:01", "broken_version": "v080503", "priority": "2", "subsystem": "Tests", "assigned_to": "", "derived_from": "", "creator": "wenger", "rust": "", "customer_group": "other", "visibility": "public", "notify": "wenger@cs.wisc.edu, tannenba@cs.wisc.edu", "due_date": ""}