{"id": 2029, "title": "Ticket #2029: leave_in_queue mixed with condor_rm leaves job in X state", "description": "<blockquote>\nSubmit a standard universe job (although I don't think it'll matter which universe) with <span class=\"quote\">leave_in_queue = True</span>. Then condor_rm it after it goes into the C state. It will stay as X in the job queue.\n\n<p>This is likely not expected.</p></blockquote>", "remarks": "<blockquote>\n</blockquote>", "derived_tickets": "", "attachments": "<html><head></head><body></body></html>", "check_ins": "", "type": "defect", "last_change": "2011-Apr-01 16:23", "status": "new", "created": "2011-Apr-01 16:23", "fixed_version": "2011-Apr-01 16:23", "broken_version": "v070506", "priority": "4", "subsystem": "Daemons", "assigned_to": "", "derived_from": "", "creator": "psilord", "rust": "", "customer_group": "other", "visibility": "public", "notify": "psilord@cs.wisc.edu", "due_date": ""}