{"id": 245, "title": "Ticket #245: Failover of HDFS file server node", "description": "<blockquote>\nExplore how using Condor's <a class=\"external\" href=\"http://www.cs.wisc.edu/condor/manual/v7.2/3_10High_Availability.html\">availability mechanisms</a> could be used to provide automatic failover of the HDFS file server node by running condor_hadoop on a backup node in case of auto-detected failure.</blockquote>", "remarks": "<blockquote>\n<em>2010-Oct-07 01:20:27 by ilikhan:</em> <br/>\n\nShould we continue to this task? See ticket <span class=\"ticket\"><a class=\"resolved\" href=\"/wiki-archive/tickets/?ticket=1682\" onclick=\"get_ticket_and_populate_wrapper('1682'); return false;\" title=\"Upgrade to new version of HDFS\">#1682</a></span></blockquote>", "derived_tickets": "<table border=\"0\" cellpadding=\"0\" cellspacing=\"0\">\n<tbody><tr><td align=\"right\" valign=\"top\" width=\"160\">\n<span class=\"ticket\"><a class=\"resolved\" href=\"/wiki-archive/tickets/?ticket=308\" onclick=\"get_ticket_and_populate_wrapper('308'); return false;\" title=\"HAD hard coded to control the negotiator\">#308</a></span></td>\n<td align=\"center\" valign=\"center\" width=\"30\">\n<span class=\"icon ptr1\">\u00a0</span></td>\n<td align=\"left\" valign=\"top\">\nHAD hard coded to control the negotiator</td></tr>\n<tr><td align=\"right\" valign=\"top\" width=\"160\">\n<span class=\"ticket\"><a class=\"abandoned\" href=\"/wiki-archive/tickets/?ticket=309\" onclick=\"get_ticket_and_populate_wrapper('309'); return false;\" title=\"HAD replication daemon can only replicate a single file\">#309</a></span></td>\n<td align=\"center\" valign=\"center\" width=\"30\">\n<span class=\"icon ptr1\">\u00a0</span></td>\n<td align=\"left\" valign=\"top\">\nHAD replication daemon can only replicate a single file</td></tr>\n<tr><td align=\"right\" valign=\"top\" width=\"160\">\n<span class=\"ticket\"><a class=\"active\" href=\"/wiki-archive/tickets/?ticket=361\" onclick=\"get_ticket_and_populate_wrapper('361'); return false;\" title=\"Export failover functionality in HDFS datanode as plugin\">#361</a></span></td>\n<td align=\"center\" valign=\"center\" width=\"30\">\n<span class=\"icon ptr1\">\u00a0</span></td>\n<td align=\"left\" valign=\"top\">\nExport failover functionality in HDFS datanode as plugin</td></tr>\n</tbody></table>", "attachments": "<html><head></head><body></body></html>", "check_ins": "<table border=\"0\" cellpadding=\"0\" cellspacing=\"0\">\n<tbody><tr><td align=\"right\" valign=\"top\" width=\"160\">2009-Jul-08 11:10</td>\n<td align=\"center\" valign=\"top\" width=\"30\">\n<span class=\"icon dot\">\u00a0</span></td>\n<td align=\"left\" valign=\"top\"> \nCheck-in <span class=\"chng\"><a href=\"https://github.com/htcondor/htcondor/commit/6ab1078dc936e573c56378d9ef7fdd816b8b991d\">[15037]</a></span>: Added ability to run secondary namenode (<span class=\"ticket\"><a class=\"active\" href=\"/wiki-archive/tickets/?ticket=4\" onclick=\"get_ticket_and_populate_wrapper('4'); return false;\" title=\"Integrate Condor with the Hadoop File System\">#4</a></span>). May be helpful in doing (<span class=\"ticket\"><a class=\"new\" href=\"/wiki-archive/tickets/?ticket=245\" onclick=\"get_ticket_and_populate_wrapper('245'); return false;\" title=\"Failover of HDFS file server node\">#245</a></span>)  (By faisal )</td></tr>\n</tbody></table>", "type": "enhance", "last_change": "2010-Nov-19 10:58", "status": "new", "created": "2009-Feb-24 10:26", "fixed_version": "2009-Feb-24 10:26", "broken_version": "", "priority": "3", "subsystem": "", "assigned_to": "faisal", "derived_from": "#4", "creator": "tannenba", "rust": "", "customer_group": "other", "visibility": "public", "notify": "", "due_date": ""}