{"id": 3769, "title": "Ticket #3769: \"condor_chirp is not a command-line tool.\" Yes it is.", "description": "<blockquote>\n<a class=\"file\" href=\"rlog?f=doc/man-pages/condor_chirp.tex\">/doc/man-pages/condor_chirp.tex</a> opens with\n\n<p></p><div class=\"code\">\n<pre class=\"code\">\\Condor{chirp} is not a command-line tool.\n</pre></div>\n\n\n<p>How is it not a command line tool?  It's an executable with no GUI, which is how I would define a command line tool.  I suspect the intent is to clarify that it's not intended for interactive use (although it might be useful under condor_ssh_to_job!).  It's intended to be used by jobs instead.  It might be good to rephrase, since the current phrasing seems confusing.</p></blockquote>", "remarks": "<blockquote>\n</blockquote>", "derived_tickets": "", "attachments": "<html><head></head><body></body></html>", "check_ins": "<table border=\"0\" cellpadding=\"0\" cellspacing=\"0\">\n<tbody><tr><td align=\"right\" valign=\"top\" width=\"160\">2013-Jul-29 10:33</td>\n<td align=\"center\" valign=\"top\" width=\"30\">\n<span class=\"icon dot\">\u00a0</span></td>\n<td align=\"left\" valign=\"top\"> \nCheck-in <span class=\"chng\"><a href=\"https://github.com/htcondor/htcondor/commit/4e42d48b891b13ddccb893fbf7a8e174e87632c8\">[37029]</a></span>: modify misleading opening sentence that says that condor_chirp is NOT a command-line tool. ===GT=== <span class=\"ticket\"><a class=\"resolved\" href=\"/wiki-archive/tickets/?ticket=3769\" onclick=\"get_ticket_and_populate_wrapper('3769'); return false;\" title='\"condor_chirp is not a command-line tool.\" Yes it is.'>#3769</a></span>  (By Karen Miller )</td></tr>\n</tbody></table>", "type": "doc", "last_change": "2013-Jul-29 10:35", "status": "resolved", "created": "2013-Jul-11 15:43", "fixed_version": "2013-Jul-11 15:43", "broken_version": "v070808", "priority": "4", "subsystem": "", "assigned_to": "smoler", "derived_from": "", "creator": "adesmet", "rust": "", "customer_group": "other", "visibility": "public", "notify": "", "due_date": ""}