{"id": 4142, "title": "Ticket #4142: Document the CONDOR_ID environment variable", "description": "<blockquote>\nJobs running in the scheduler universe get an environment variable \"CONDOR_ID\" which contains the clusterID of the instance. I found this by experiment and by looking at source; however it is undocumented (CONDOR_IDS is an unrelated setting). It appears to be there for the benefit of Pegasus and possibly other similar tools.\n\n<p>It can be useful to know the cluster ID of the condor_dagman job while it is running. For example, if you are keeping track of DAG submissions in an external database, a FINAL node or a SUBDAG EXTERNAL SCRIPT POST can update the database row with the DAG result, using CONDOR_ID to locate the row to update.\n\n</p><p>I am suggesting that this feature be documented so that it can be used and relied upon.\n\n</p><p>Discussion at <a class=\"external\" href=\"https://lists.cs.wisc.edu/archive/htcondor-users/2013-December/msg00130.shtml\">https://lists.cs.wisc.edu/archive/htcondor-users/2013-December/msg00130.shtml</a></p></blockquote>", "remarks": "<blockquote>\n</blockquote>", "derived_tickets": "", "attachments": "<html><head></head><body></body></html>", "check_ins": "<table border=\"0\" cellpadding=\"0\" cellspacing=\"0\">\n<tbody><tr><td align=\"right\" valign=\"top\" width=\"160\">2015-Jan-05 15:14</td>\n<td align=\"center\" valign=\"top\" width=\"30\">\n<span class=\"icon dot\">\u00a0</span></td>\n<td align=\"left\" valign=\"top\"> \nCheck-in <span class=\"chng\"><a href=\"https://github.com/htcondor/htcondor/commit/9cdc31a18b3e4996dc4130914e8fbb43a0b5015b\">[42106]</a></span>: document and correct index entries for environment variables CONDOR_ID and CONDOR_IDS <span class=\"ticket\"><a class=\"resolved\" href=\"/wiki-archive/tickets/?ticket=4142\" onclick=\"get_ticket_and_populate_wrapper('4142'); return false;\" title=\"Document the CONDOR_ID environment variable\">#4142</a></span>  (By Karen Miller )</td></tr>\n</tbody></table>", "type": "doc", "last_change": "2015-Jan-05 15:16", "status": "resolved", "created": "2013-Dec-30 09:44", "fixed_version": "2013-Dec-30 09:44", "broken_version": "v080000", "priority": "4", "subsystem": "", "assigned_to": "smoler", "derived_from": "", "creator": "b.candler", "rust": "", "customer_group": "other", "visibility": "public", "notify": "b.candler@pobox.com", "due_date": ""}