{"id": 5847, "title": "Ticket #5847: Have DAGMan maintain a connection to the schedd", "description": "<blockquote>\nRe discussion with Greg and TJ: DAGMan should create a connection to the appropriate schedd at startup, and maintain that connection as long as it's running.  Then use that connection to directly submit and remove jobs via the API, as opposed to forking condor_submit and condor_rm.</blockquote>", "remarks": "<blockquote>\n</blockquote>", "derived_tickets": "", "attachments": "<html><head></head><body></body></html>", "check_ins": "", "type": "enhance", "last_change": "2016-Aug-17 11:12", "status": "new", "created": "2016-Aug-17 11:12", "fixed_version": "2016-Aug-17 11:12", "broken_version": "v080506", "priority": "4", "subsystem": "Dag", "assigned_to": "", "derived_from": "", "creator": "wenger", "rust": "", "customer_group": "other", "visibility": "public", "notify": "wenger@cs.wisc.edu", "due_date": ""}