{"id": 604, "title": "Ticket #604: Does this leak memory (matchmaker.cpp)", "description": "<blockquote>\n<a class=\"file\" href=\"rlog?f=src/condor_negotiator.V6/matchmaker.cpp\">/src/condor_negotiator.V6/matchmaker.cpp</a>, around line 1571, in obtainAdsFromCollector, includes:\n<div class=\"code\">\n<pre class=\"code\">\t\t\t// TODO: Does this leak memory?\n\t\t\tnegReqTree = ad-&gt;Lookup(ATTR_NEGOTIATOR_REQUIREMENTS);\n</pre></div>\n\n\n<p>Task: Determine if it leaks memory.  Does it? Fix it.  Does it not? Remove the comment.</p></blockquote>", "remarks": "<blockquote>\n<hr/>\n<em>2010-Aug-23 17:07:50 by adesmet:</em> <br/>\n\nBulk change of target version from v070402 to v070404 using ./ticket_target_mover.\n<hr/>\n<em>2010-Oct-27 16:39:01 by adesmet:</em> <br/>\n\nBulk change of target version from v070404 to v070405 using ./ticket-target-mover.\n\n<p></p><hr/>\n<em>2013-Jun-04 14:46:32 by tannenba:</em> <br/>\n\nIt does not leak memory.  Removed misleading comment, added a comment\ntelling future worry-worts that a static buffer (sigh) is used. Resolving.\nP.s. obviously no need for a version history entry here.</blockquote>", "derived_tickets": "", "attachments": "<html><head></head><body></body></html>", "check_ins": "<table border=\"0\" cellpadding=\"0\" cellspacing=\"0\">\n<tbody><tr><td align=\"right\" valign=\"top\" width=\"160\">2013-Jun-04 14:45</td>\n<td align=\"center\" valign=\"top\" width=\"30\">\n<span class=\"icon dot\">\u00a0</span></td>\n<td align=\"left\" valign=\"top\"> \nCheck-in <span class=\"chng\"><a href=\"https://github.com/htcondor/htcondor/commit/2108f3f256796710b4b9f652f1e528326e7106b9\">[35988]</a></span>: Remove misleading comment about leaking memory. <span class=\"ticket\"><a class=\"resolved\" href=\"/wiki-archive/tickets/?ticket=604\" onclick=\"get_ticket_and_populate_wrapper('604'); return false;\" title=\"Does this leak memory (matchmaker.cpp)\">#604</a></span>  (By Todd Tannenbaum )</td></tr>\n</tbody></table>", "type": "defect", "last_change": "2013-Jun-04 14:48", "status": "resolved", "created": "2009-Jun-24 17:50", "fixed_version": "2009-Jun-24 17:50", "broken_version": "", "priority": "4", "subsystem": "DaemonsCM", "assigned_to": "tannenba", "derived_from": "", "creator": "adesmet", "rust": "", "customer_group": "other", "visibility": "public", "notify": "", "due_date": ""}