{"id": 6368, "title": "Ticket #6368: Improve HTCondor installation for RPM instructions", "description": "<blockquote>\n1. The RPM install instructions in the HTCondor Manual do not match the\nRPM install instructions on the web site.  Perhaps the manual repo\ninstall instructions should be removed and just point to the web site?\n\n<p>2. The RPM installation instructions on the web for RHEL7, even for our\ncurrent stable and dev release, still talk about the need to disable\nSELinux at the top of the page.  This is no longer true as of HTCondor\nv8.6.x, right?\n\n</p><p>3. The repo transfers, including grabbing the signing key, are all via\nhttp.  Shouldn't it be via https ?</p></blockquote>", "remarks": "<blockquote>\n<em>2017-Aug-08 13:22:02 by tim:</em> <br/>\n\nRemoved SELinux warning from web pages and pushed to web site.</blockquote>", "derived_tickets": "", "attachments": "<html><head></head><body></body></html>", "check_ins": "<table border=\"0\" cellpadding=\"0\" cellspacing=\"0\">\n<tbody><tr><td align=\"right\" valign=\"top\" width=\"160\">2018-Oct-30 10:35</td>\n<td align=\"center\" valign=\"top\" width=\"30\">\n<span class=\"icon dot\">\u00a0</span></td>\n<td align=\"left\" valign=\"top\"> \nCheck-in <span class=\"chng\"><a href=\"https://github.com/htcondor/htcondor/commit/5ae433404d15ea8ced4be432b0b7036539859793\">[55648]</a></span>: Prepare for final build (<span class=\"ticket\"><a class=\"resolved\" href=\"/wiki-archive/tickets/?ticket=6387\" onclick=\"get_ticket_and_populate_wrapper('6387'); return false;\" title=\"User Python Module\">#6387</a></span>, <span class=\"ticket\"><a class=\"resolved\" href=\"/wiki-archive/tickets/?ticket=5843\" onclick=\"get_ticket_and_populate_wrapper('5843'); return false;\" title=\"Manual does not contain any documentation on SYSLOG knobs\">#5843</a></span>, <span class=\"ticket\"><a class=\"resolved\" href=\"/wiki-archive/tickets/?ticket=6368\" onclick=\"get_ticket_and_populate_wrapper('6368'); return false;\" title=\"Improve HTCondor installation for RPM instructions\">#6368</a></span>)  (By Tim Theisen )</td></tr>\n</tbody></table>", "type": "doc", "last_change": "2018-Oct-30 10:36", "status": "resolved", "created": "2017-Aug-08 13:13", "fixed_version": "2017-Aug-08 13:13", "broken_version": "", "priority": "4", "subsystem": "Packaging", "assigned_to": "tim", "derived_from": "", "creator": "tim", "rust": "", "customer_group": "users", "visibility": "public", "notify": "tannenba@cs.wisc.edu blin@cs.wisc.edu", "due_date": ""}