{"id": 7494, "title": "Ticket #7494: Update doc: Queue from shell command using pipe", "description": "<blockquote>\n<a class=\"external\" href=\"https://github.com/htcondor/htcondor/pull/101\">https://github.com/htcondor/htcondor/pull/101</a>\n\n<p>Undocumented condor feature, but the described syntax works in my experiments.\n\n</p><p>Example: \"Queue from seq 7 9 |\"\n\n</p><p>I think this should be documented (and I believe it used to be).\n\n</p><p>tried on:\n</p><div class=\"verbatim\">\n<pre>$CondorVersion: 8.6.11 May 10 2018 BuildID: 440910 $\n$CondorPlatform: x86_64_Ubuntu14 $\n</pre></div>\n</blockquote>", "remarks": "<blockquote>\n<hr/>\n<em>2020-Apr-10 07:43:03 by tim:</em> <br/>\n\nBulk change of target version from v080808 to v080809 using ticket-target-mover.</blockquote>", "derived_tickets": "", "attachments": "<html><head></head><body></body></html>", "check_ins": "<table border=\"0\" cellpadding=\"0\" cellspacing=\"0\">\n<tbody><tr><td align=\"right\" valign=\"top\" width=\"160\">2020-Feb-07 14:23</td>\n<td align=\"center\" valign=\"top\" width=\"30\">\n<span class=\"icon dot\">\u00a0</span></td>\n<td align=\"left\" valign=\"top\"> \nCheck-in <span class=\"chng\"><a href=\"https://github.com/htcondor/htcondor/commit/3f375a05c4c6a33a5064a92f46cc59067faaf236\">[58926]</a></span>: Merged <span class=\"chng\"><a href=\"https://github.com/htcondor/htcondor/commit/95e1cd5c6aa451cc59e56706bbda4d7f2cf8259b\">[58925]</a></span>, Merge branch 'V8_9-pr101' <span class=\"ticket\"><a class=\"resolved\" href=\"/wiki-archive/tickets/?ticket=7494\" onclick=\"get_ticket_and_populate_wrapper('7494'); return false;\" title=\"Update doc: Queue from shell command using pipe\">#7494</a></span>  (By Tim Theisen )</td></tr>\n</tbody></table>", "type": "doc", "last_change": "2020-Apr-10 07:43", "status": "resolved", "created": "2020-Feb-07 14:23", "fixed_version": "2020-Feb-07 14:23", "broken_version": "", "priority": "4", "subsystem": "Tools", "assigned_to": "tim", "derived_from": "", "creator": "tim", "rust": "", "customer_group": "other", "visibility": "public", "notify": "", "due_date": ""}