{"id": 7712, "title": "Ticket #7712: Add \"--debug\" option to bosco_cluster", "description": "<blockquote>\nThis will help us understand the nature of the SSH failures for the Hosted CE</blockquote>", "remarks": "<blockquote>\n</blockquote>", "derived_tickets": "", "attachments": "<html><head></head><body></body></html>", "check_ins": "<table border=\"0\" cellpadding=\"0\" cellspacing=\"0\">\n<tbody><tr><td align=\"right\" valign=\"top\" width=\"160\">2020-Jul-31 17:39</td>\n<td align=\"center\" valign=\"top\" width=\"30\">\n<span class=\"icon dot\">\u00a0</span></td>\n<td align=\"left\" valign=\"top\"> \nCheck-in <span class=\"chng\"><a href=\"https://github.com/htcondor/htcondor/commit/e6bba0dd8ab06eb53c3fcffe36bd85632ea55ef2\">[60298]</a></span>: Version history for <span class=\"ticket\"><a class=\"resolved\" href=\"/wiki-archive/tickets/?ticket=7500\" onclick=\"get_ticket_and_populate_wrapper('7500'); return false;\" title=\"Clients should not suggest authentication methods they don't support\">#7500</a></span>, <span class=\"ticket\"><a class=\"resolved\" href=\"/wiki-archive/tickets/?ticket=7627\" onclick=\"get_ticket_and_populate_wrapper('7627'); return false;\" title=\"Support CPU affinity with Docker\">#7627</a></span>, <span class=\"ticket\"><a class=\"resolved\" href=\"/wiki-archive/tickets/?ticket=7647\" onclick=\"get_ticket_and_populate_wrapper('7647'); return false;\" title=\"UW condor 8.9.7 RPM does not pull in Python bindings\">#7647</a></span>, <span class=\"ticket\"><a class=\"resolved\" href=\"/wiki-archive/tickets/?ticket=7712\" onclick=\"get_ticket_and_populate_wrapper('7712'); return false;\" title='Add \"--debug\" option to bosco_cluster'>#7712</a></span>, <span class=\"ticket\"><a class=\"resolved\" href=\"/wiki-archive/tickets/?ticket=7753\" onclick=\"get_ticket_and_populate_wrapper('7753'); return false;\" title=\"RHEL-based Bosco tarballs using the wrong version\">#7753</a></span>  (By Tim Theisen )</td></tr>\n<tr><td align=\"right\" valign=\"top\" width=\"160\">2020-Jun-25 10:17</td>\n<td align=\"center\" valign=\"top\" width=\"30\">\n<span class=\"icon dot\">\u00a0</span></td>\n<td align=\"left\" valign=\"top\"> \nCheck-in <span class=\"chng\"><a href=\"https://github.com/htcondor/htcondor/commit/e58dca49c12787ffe28e9c8fbe744150b156e1af\">[59989]</a></span>: Apply fixes from code review <span class=\"ticket\"><a class=\"resolved\" href=\"/wiki-archive/tickets/?ticket=7712\" onclick=\"get_ticket_and_populate_wrapper('7712'); return false;\" title='Add \"--debug\" option to bosco_cluster'>#7712</a></span> Co-authored-by: edquist &lt;edquist@users.noreply.github.com&gt; Committer: <span class=\"wiki\"><a class=\"missing\" href=\"wiki?p=GitHub\" title=\"Git Hub\">GitHub</a></span>  (By Brian Lin )</td></tr>\n<tr><td align=\"right\" valign=\"top\" width=\"160\">2020-Jun-12 16:02</td>\n<td align=\"center\" valign=\"top\" width=\"30\">\n<span class=\"icon dot\">\u00a0</span></td>\n<td align=\"left\" valign=\"top\"> \nCheck-in <span class=\"chng\"><a href=\"https://github.com/htcondor/htcondor/commit/daac5073cfcc829e39dc47581eddf684cefb9803\">[59988]</a></span>: Add \"--debug\" option to bosco_cluster <span class=\"ticket\"><a class=\"resolved\" href=\"/wiki-archive/tickets/?ticket=7712\" onclick=\"get_ticket_and_populate_wrapper('7712'); return false;\" title='Add \"--debug\" option to bosco_cluster'>#7712</a></span>  (By Brian Lin )</td></tr>\n</tbody></table>", "type": "enhance", "last_change": "2020-Jul-31 17:40", "status": "resolved", "created": "2020-Jun-25 11:19", "fixed_version": "2020-Jun-25 11:19", "broken_version": "", "priority": "3", "subsystem": "Grid", "assigned_to": "tim", "derived_from": "", "creator": "tim", "rust": "", "customer_group": "osg", "visibility": "public", "notify": "", "due_date": ""}