{"id": 993, "title": "Ticket #993: condor_submit without Globus gives misleading error message", "description": "<blockquote>\nBuild condor on a platform that normally has Globus support, but turn it off in configure.  Given the resulting binaries, try to run condor_submit for a universe=cream job and a valid x509userproxy=/path/to/it.\n\n<p>Expected output: \"This version of Condor was built without Globus support, and cannot process this job.\"\n\n</p><p>Actual output: \"ERROR: can't determine proxy filename\"\n\n</p><p>Discovered when some merges unexpectedly left me building sans Globus.</p></blockquote>", "remarks": "<blockquote>\n<hr/>\n<em>2010-Oct-20 16:03:30 by jfrey:</em> <br/>\n\nBulk change of target version from v070504 to v070505 using ./ticket-target-mover.\n<hr/>\n<em>2011-Jan-27 14:46:04 by danb:</em> <br/>\n\nBulk change of target version from v070505 to v070506 using ./ticket-target-mover.\n<hr/>\n<em>2011-Feb-01 14:49:30 by tannenba:</em> <br/>\n\nBulk change of target version from v070506 to NULL using ./ticket-target-mover.</blockquote>", "derived_tickets": "", "attachments": "<html><head></head><body></body></html>", "check_ins": "", "type": "defect", "last_change": "2011-Feb-01 14:52", "status": "new", "created": "2009-Nov-20 17:41", "fixed_version": "2009-Nov-20 17:41", "broken_version": "v070400", "priority": "4", "subsystem": "", "assigned_to": "", "derived_from": "", "creator": "adesmet", "rust": "", "customer_group": "other", "visibility": "public", "notify": "", "due_date": ""}